Workbook

Sheet 1.资产总览
A1: Anson 家庭房产持有/出售决策表
A2: 数据日期：2026-09-13 | 单价来源：安居客/房天下/贝壳 2026年8-9月参考价 | 蓝色=输入值，黄色=待核实假设值
A4: 序号 | B4: 房产名称 | C4: 城市/区域 | D4: 权利人 | E4: 产权性质 | F4: 建筑面积(㎡) | G4: 原购单价(元/㎡) | H4: 原购总价(元) | I4: 现参考单价(元/㎡) | J4: 当前市值(元) | K4: 涨跌幅 | L4: 建议处置 | M4: 出售优先级
A5: 1 | B5: 孔雀城泊心园 0015#3-602 | C5: 廊坊固安 | D5: 杜岩松 | E5: 住宅(商品房) | F5: 114.21 | G5: 7000 | H5: =F5*G5 -> 799470 | I5: 9500 | J5: =F5*I5 -> 1084995 | K5: =(I5-G5)/G5 -> 0.35714286 | L5: 出售 | M5: 高
A6: 2 | B6: 孔雀城领航城二区19-1-2301 | C6: 廊坊广阳·万庄 | D6: 朱江妍 | E6: 住宅(商品房) | F6: 124.19 | G6: 17000 | H6: =F6*G6 -> 2111230 | I6: 6395 | J6: =F6*I6 -> 794195.05 | K6: =(I6-G6)/G6 -> -0.62382353 | L6: 出售 | M6: 高
A7: 3 | B7: 孔雀城大学里 GY5-4-1802 | C7: 廊坊开发区 | D7: 杜岩松 | E7: 公寓(商业) | F7: 71.56 | G7: 5000 | H7: =F7*G7 -> 357800 | I7: 6000 | J7: =F7*I7 -> 429360 | K7: =(I7-G7)/G7 -> 0.2 | L7: 出售 | M7: 中
A8: 4 | B8: 恒大城市之光二期 | C8: 深圳龙岗·中心城 | D8: Anson | E8: 公寓(商业) | F8: 72 | G8: 25000 | H8: =F8*G8 -> 1800000 | I8: 18000 | J8: =F8*I8 -> 1296000 | K8: =(I8-G8)/G8 -> -0.28 | L8: 出售 | M8: 中
A9: 5 | B9: 佳乐国际城 35-2-22-1 | C9: 成都新都·三河 | D9: 刘丽英(岳母) | E9: 住宅(商品房) | F9: 108.2 | G9: 6500 | H9: =F9*G9 -> 703300 | I9: 9750 | J9: =F9*I9 -> 1054950 | K9: =(I9-G9)/G9 -> 0.5 | L9: 自住则留/空置则卖 | M9: 低
B10: 合计（5 套） | F10: =SUM(F5:F9) -> 490.16 | H10: =SUM(H5:H9) -> 5771800 | J10: =SUM(J5:J9) -> 4659500 | K10: =IF(H10=0,0,(J10-H10)/H10) -> -0.19271284
A12: 注：市值按同小区参考均价估算，非实际成交价；原购总价未计契税、维修基金、贷款利息，实际盈亏应再扣减资金成本。

Sheet 2.价格与税费测算
A1: 逐套价格建议与卖方税费测算（人民币·元）
A2: 住宅：满2年免增值税，满五唯一免个税；公寓(商业)：差额5.6%增值税及附加 + 核定5%土地增值税 + 核定3%个税 + 0.05%印花税。税率为估算，以属地税务核定为准。
A4: 房产名称 | B4: 建议挂牌价 | C4: 目标成交价 | D4: 心理底价 | E4: 增值税及附加 | F4: 个人所得税 | G4: 土地增值税 | H4: 印花税 | I4: 中介费(2%) | J4: 卖方税费合计 | K4: 预计到手价 | L4: 相对原值盈亏(到手价口径)
A5: 孔雀城泊心园 | B5: 1100000 | C5: 1050000 | D5: 1000000 | E5: 0 | F5: 0 | G5: 0 | H5: 0 | I5: =C5*0.02 -> 21000 | J5: =SUM(E5:I5) -> 21000 | K5: =C5-J5 -> 1029000 | L5: =K5-'1.资产总览'!H5 -> 229530
A6: 孔雀城领航城二区 | B6: 850000 | C6: 795000 | D6: 760000 | E6: 0 | F6: 0 | G6: 0 | H6: 0 | I6: =C6*0.02 -> 15900 | J6: =SUM(E6:I6) -> 15900 | K6: =C6-J6 -> 779100 | L6: =K6-'1.资产总览'!H6 -> -1332130
A7: 孔雀城大学里(公寓) | B7: 480000 | C7: 430000 | D7: 400000 | E7: 4043 | F7: 12900 | G7: 21500 | H7: 215 | I7: =C7*0.02 -> 8600 | J7: =SUM(E7:I7) -> 47258 | K7: =C7-J7 -> 382742 | L7: =K7-'1.资产总览'!H7 -> 24942
A8: 恒大城市之光二期(公寓) | B8: 1380000 | C8: 1296000 | D8: 1200000 | E8: 0 | F8: 0 | G8: 64800 | H8: 648 | I8: =C8*0.02 -> 25920 | J8: =SUM(E8:I8) -> 91368 | K8: =C8-J8 -> 1204632 | L8: =K8-'1.资产总览'!H8 -> -595368
A9: 佳乐国际城 | B9: 1100000 | C9: 1030000 | D9: 970000 | E9: 0 | F9: 10300 | G9: 0 | H9: 0 | I9: =C9*0.02 -> 20600 | J9: =SUM(E9:I9) -> 30900 | K9: =C9-J9 -> 999100 | L9: =K9-'1.资产总览'!H9 -> 295800
A10: 合计 | B10: =SUM(B5:B9) -> 4910000 | C10: =SUM(C5:C9) -> 4601000 | D10: =SUM(D5:D9) -> 4330000 | E10: =SUM(E5:E9) -> 4043 | F10: =SUM(F5:F9) -> 23200 | G10: =SUM(G5:G9) -> 86300 | H10: =SUM(H5:H9) -> 863 | I10: =SUM(I5:I9) -> 92020 | ... L10: =SUM(L5:L9) -> -1377226
A12: 税费口径说明：
A13: · 泊心园 / 领航城：已满2年且为家庭唯一住房，增值税、个税双双免征（需确认契税缴纳时间以认定满五）。
A14: · 大学里：商业公寓，按成交价核定征收，实际税负可能因属地不同上下浮动，务必先到税务窗口试算。
A15: · 恒大城市之光：原值180万高于现价，差额增值税为0；但土增税多按核定征收，亏损也要交，是公寓最大的税务痛点。
A16: · 佳乐国际城：若契税缴纳已满5年且为唯一住房，个税10,300元可全免，到手价上浮约1万。
A17: · 底价以下建议改为出租持有，不割肉。

Sheet 3.持有成本
A1: 持有成本与现金流对比（元/年）
A2: 物业费、租金为估算值（黄色），需按实际合同核对。
A4: 房产名称 | B4: 年物业费 | C4: 年采暖/其他 | D4: 年租金收入 | E4: 年净现金流 | F4: 使用状态 | G4: 结论
A5: 孔雀城泊心园 | B5: 2741 | C5: 2513 | D5: 18000 | E5: =D5-B5-C5 -> 12746 | F5: 空置 | G5: 环京空置即纯亏，尽快出售
A6: 孔雀城领航城二区 | B6: 2981 | C6: 2732 | D6: 19200 | E6: =D6-B6-C6 -> 13487 | F6: 空置 | G6: 同上，且已亏63%
A7: 孔雀城大学里(公寓) | B7: 2576 | C7: 1200 | D7: 13200 | E7: =D7-B7-C7 -> 9424 | F7: 空置 | G7: 商业性质，租金低、税费重，出售
A8: 恒大城市之光二期(公寓) | B8: 3024 | C8: 0 | D8: 33600 | E8: =D8-B8-C8 -> 30576 | F8: 出租 | G8: 深圳租金可覆盖成本，但公寓升值弱，可择机卖
A9: 佳乐国际城 | B9: 2597 | C9: 800 | D9: 27600 | E9: =D9-B9-C9 -> 24203 | F9: 岳母自住? | G9: 若自住则保留；空置则出售回笼现金

Sheet 4.假设与数据来源
A1: 关键假设与数据来源
A3: 项目 | B3: 取值 | C3: 性质 | D3: 来源 / 说明
A4: 孔雀城泊心园 参考单价 | B4: 9,500 元/㎡ | C4: 外部行情 | D4: 房天下 2026年8月参考价 9,536 元/㎡；同户型114.21㎡挂牌9,456元/㎡
A5: 孔雀城领航城 参考单价 | B5: 6,395 元/㎡ | C5: 外部行情 | D5: 安居客小区均价 6,395 元/㎡（廊坊广阳·万庄）
A6: 孔雀城大学里 参考单价 | B6: 6,000 元/㎡ | C6: 估算(待核实) | D6: 贝壳参考均价 7,666 元/㎡（含住宅），公寓通常折价20-40%，取6,000
A7: 大学里 原购单价 | B7: 5,000 元/㎡ | C7: 假设(待核实) | D7: 未提供原始购房价，按2016年前后廊坊开发区公寓价假设，请更新
A8: 恒大城市之光 参考单价 | B8: 18,000 元/㎡ | C8: 估算(待核实) | D8: 安居客 17,252 元/㎡（公寓口径）；房天下2022年参考价 20,402 元/㎡，取中间值
A9: 佳乐国际城 参考单价 | B9: 9,750 元/㎡ | C9: 估算(待核实) | D9: 楼盘网一期参考价12,973元/㎡偏虚高；房天下挂牌9,480–10,000元/㎡，新都区均价8,011元/㎡
A10: 佳乐国际城 原购单价 | B10: 6,500 元/㎡ | C10: 假设(待核实) | D10: 未提供原购价，仅用于计算，请按实际购房发票更新
A11: 中介费率 | B11: 2% | C11: 假设 | D11: 卖方承担口径，实际可谈至1%–1.5%
A12: 公寓增值税及附加率 | B12: 5.6% | C12: 政策口径 | D12: 差额×5%增值税 + 附加税费约12%（增值税的）
A13: 公寓土地增值税 | B13: 核定5% | C13: 政策口径 | D13: 各地核定率不同（常见3%–6%），以属地税务核定为准
A14: 公寓个税 | B14: 核定3% | C14: 政策口径 | D14: 非住宅转让，部分地区按差额20%据实征收
... A17: 租金水平 | B17: 见Sheet3 | C17: 估算 | D17: 需按实际租赁合同或市场租金更新
